{"2021-1-21":[{"name":"COGS 120","type":"School","start":"10:00 AM","end":"4:10 PM","duration":22200},{"name":"Lunch","type":"Family","start":"12:30 PM","end":"1:30 PM","duration":3600},{"name":"Game","type":"Fun","start":"8:00 PM","end":"12:00 AM","duration":14400},{"name":"COGS 120","type":"School","start":"4:05 AM","end":"11:00 AM","duration":24900},{"name":"COGS 120","type":"School","start":"1:00 AM","end":"11:00 AM","duration":36000}],"2021-1-23":[{"name":"COGS 120","type":"School","start":"8:00 AM","end":"9:00 AM","duration":3600},{"name":"COGS 102B","type":"School","start":"3:30 PM","end":"5:00 PM","duration":5400},{"name":"COGS 120","type":"School","start":"4:00 PM","end":"7:00 PM","duration":10800},{"name":"COGS 120","type":"School","start":"3:00 PM","end":"7:00 PM","duration":14400}],"2021-1-24":[{"name":"COGS 120","type":"Fun","start":"4:00 AM","end":"12:00 AM","duration":72000}]}
{"harry":{"2/24/2021":[{"name":"COGS 120","type":"School","start":"10:00 AM","end":"4:00 PM","duration":21600},{"name":"Sleep","type":"Other","start":"6:00 PM","end":"10:00 PM","duration":14400},{"name":"Lunch","type":"Family","start":"9:00 PM","end":"10:00 PM","duration":3600}],"2/19/2021":[{"name":"COGS 120","type":"School","start":"10:00 AM","end":"4:00 PM","duration":100000}],"2/5/2021":[{"name":"COGS 120","type":"Fun","start":"10:00 AM","end":"4:00 PM","duration":123456}]}}
